base_tokenizer.py
cluster_estimator.py
code2parquet_local_ray.py
code2parquet_s3_ray.py
code2parquet_transform_ray.py
code_quality_local_ray.py
code_quality_s3_ray.py
code_quality_transform_ray.py
compute_shingles.py
doc_chunk_local_ray.py
doc_chunk_s3_ray.py
doc_chunk_transform_ray.py
doc_id_local_ray.py
doc_id_s3_ray.py
doc_id_transform_ray.py
doc_quality_local_ray.py
doc_quality_s3_ray.py
doc_quality_transform_ray.py
ededup_local_ray.py
ededup_local_ray_incremental.py
ededup_s3_ray.py
ededup_transform_ray.py
fdedup_local_ray.py
fdedup_s3_ray.py
fdedup_support.py
fdedup_transform_ray.py
filter_local_ray.py
filter_s3_ray.py
filter_transform_ray.py
header_cleanser_local_ray.py
header_cleanser_s3_ray.py
header_cleanser_transform_ray.py
lang_id_local_ray.py
lang_id_s3_ray.py
lang_id_transform_ray.py
pdf2parquet_local_ray.py
pdf2parquet_s3_ray.py
pdf2parquet_transform_ray.py
pii_redactor_local_ray.py
pii_redactor_s3_ray.py
pii_redactor_transform_ray.py
profiler_local_ray.py
profiler_s3_ray.py
profiler_transform_ray.py
proglang_select_local_ray.py
proglang_select_transform_ray.py
repo_level_order_local_ray.py
repo_level_order_s3_ray.py
repo_level_order_transform.py
repo_level_order_transform_ray.py
resize_local_ray.py
resize_s3_ray.py
resize_transform_ray.py
text_encoder_local_ray.py
text_encoder_s3_ray.py
text_encoder_transform_ray.py
tokenization_local_ray.py
tokenization_s3_ray.py
tokenization_transform_ray.py
dpk_repo_level_order/__init__.py
dpk_repo_level_order/internal/check_languages.py
dpk_repo_level_order/internal/repo_grouper.py
dpk_repo_level_order/internal/repo_level_wrappers.py
dpk_repo_level_order/internal/sorting/semantic_ordering/__init__.py
dpk_repo_level_order/internal/sorting/semantic_ordering/build_dep_graph.py
dpk_repo_level_order/internal/sorting/semantic_ordering/sort_by_semantic_dep.py
dpk_repo_level_order/internal/sorting/semantic_ordering/topological_sort.py
dpk_repo_level_order/internal/sorting/semantic_ordering/utils.py
data_prep_toolkit_transforms_ray-0.2.1.dist-info/METADATA
data_prep_toolkit_transforms_ray-0.2.1.dist-info/WHEEL
data_prep_toolkit_transforms_ray-0.2.1.dist-info/top_level.txt
data_prep_toolkit_transforms_ray-0.2.1.dist-info/RECORD
