Metadata-Version: 2.1
Name: data_prep_toolkit_transforms_ray
Version: 0.2.1
Summary: Data Preparation Toolkit Transforms using Ray
Author-email: Maroun Touma <touma@us.ibm.com>
License: Apache-2.0
Keywords: transforms,data preprocessing,data preparation,llm,generative,ai,fine-tuning,llmapps
Requires-Python: <3.12,>=3.10
Requires-Dist: data-prep-toolkit-ray>=0.2.1
Requires-Dist: data-prep-toolkit-transforms>=0.2.1
Requires-Dist: parameterized
Requires-Dist: tqdm==4.66.3
Requires-Dist: mmh3==4.1.0
Requires-Dist: xxhash==3.4.1
Requires-Dist: scipy>=1.12.0
Requires-Dist: networkx==3.3
Requires-Dist: colorlog==6.8.2
Requires-Dist: func-timeout==4.3.5
Requires-Dist: pandas==2.2.2
Requires-Dist: emerge-viz==2.0.0
Requires-Dist: scancode-toolkit==32.1.0; platform_system != "Darwin"
